enyo/__init__.py
enyo/enyodecryption.py
enyo/enyoencryption.py
enyo-0.1.1.dist-info/LICENSE
enyo-0.1.1.dist-info/METADATA
enyo-0.1.1.dist-info/WHEEL
enyo-0.1.1.dist-info/top_level.txt
enyo-0.1.1.dist-info/RECORD
