Metadata-Version: 2.1
Name: enyo
Version: 0.1.1
Summary: Enyo is a lightweight multistage partition-based encryption algorithm. Enyo cipher demonstrates good resistance to a brute-force attack. It is well suited for small-scale applications where the computational power is a bottleneck.
Home-page: https://github.com/apratimshukla6/enyo
Author: Apratim Shukla, Mayank Tolani, Dipan Polley, Abhishek TK
Author-email: apratimshukla6@gmail.com
License: MIT
Download-URL: https://pypi.org/project/enyo/
Keywords: Enyo,EnyoCipher,EnyoEncryption
Platform: UNKNOWN
License-File: LICENSE
